Workbook

Sheet Comparison
A1: Metric | B1: Tata Consumer FY26 | C1: Goodricke FY26 | D1: United Nilgiri FY26 | E1: Tata Consumer 5-yr avg | F1: Goodricke 5-yr avg | G1: United Nilgiri 5-yr avg
A2: Sales (₹ Cr) | B2: ='Tata Consumer'!G2 -> 20290.43 | C2: =Goodricke!G2 -> 801.29 | D2: ='United Nilgiri'!G2 -> 83.35 | E2: =AVERAGE('Tata Consumer'!C2:G2) -> 15864.622 | F2: =AVERAGE(Goodricke!C2:G2) -> 852.006 | G2: =AVERAGE('United Nilgiri'!C2:G2) -> 83.296
A3: Sales CAGR, 5 yrs | B3: ='Tata Consumer'!B23 -> 0.11828231 | C3: =Goodricke!B23 -> -0.021123665 | D3: ='United Nilgiri'!B23 -> 0.046772289
A4: Revenue growth, latest year | B4: ='Tata Consumer'!G21 -> 0.15166787 | C4: =Goodricke!G21 -> -0.13787872 | D4: ='United Nilgiri'!G21 -> -0.071826281 | E4: =AVERAGE('Tata Consumer'!C21:G21) -> 0.11875617 | F4: =AVERAGE(Goodricke!C21:G21) -> -0.016174585 | G4: =AVERAGE('United Nilgiri'!C21:G21) -> 0.04956528
A5: EBITDA margin | B5: ='Tata Consumer'!G17 -> 0.13759196 | C5: =Goodricke!G17 -> 0.024310799 | D5: ='United Nilgiri'!G17 -> 0.23791242 | E5: =AVERAGE('Tata Consumer'!C17:G17) -> 0.14030983 | F5: =AVERAGE(Goodricke!C17:G17) -> 0.0057386754 | G5: =AVERAGE('United Nilgiri'!C17:G17) -> 0.18311844
A6: Net margin | B6: ='Tata Consumer'!G18 -> 0.076011203 | C6: =Goodricke!G18 -> 0.031886084 | D6: ='United Nilgiri'!G18 -> 0.26322735 | E6: =AVERAGE('Tata Consumer'!C18:G18) -> 0.077374982 | F6: =AVERAGE(Goodricke!C18:G18) -> -0.0049166246 | G6: =AVERAGE('United Nilgiri'!C18:G18) -> 0.18825412
A7: ROE | B7: ='Tata Consumer'!G19 -> 0.070788199 | C7: =Goodricke!G19 -> 0.084184514 | D7: ='United Nilgiri'!G19 -> 0.090927929 | E7: =AVERAGE('Tata Consumer'!C19:G19) -> 0.068421343 | F7: =AVERAGE(Goodricke!C19:G19) -> -0.022718037 | G7: =AVERAGE('United Nilgiri'!C19:G19) -> 0.075387582
A8: Asset turnover (x) | B8: ='Tata Consumer'!G20 -> 0.59192462 | C8: =Goodricke!G20 -> 1.3383832 | D8: ='United Nilgiri'!G20 -> 0.32603168 | E8: =AVERAGE('Tata Consumer'!C20:G20) -> 0.57719129 | F8: =AVERAGE(Goodricke!C20:G20) -> 1.3465554 | G8: =AVERAGE('United Nilgiri'!C20:G20) -> 0.38515883
A9: Market cap (₹ Cr) | B9: 95396.99 | C9: 453.82 | D9: 203.73
A10: P/E (market cap ÷ FY26 net profit) | B10: =B9/'Tata Consumer'!G10 -> 61.853718 | C10: =C9/Goodricke!G10 -> 17.762035 | D10: =D9/'United Nilgiri'!G10 -> 9.2857794
A12: 5-yr avg = average of FY22 to FY26 (five years). Green = values pulled from the other sheets. Blue = typed from the Screener Data Sheet export.
A13: Market caps are the prices in your downloaded Screener files, so they change daily. Refresh them before you finalise the report.
A14: Tata Consumer also sells coffee, salt and foods, so its numbers are not tea-only. EV/EBITDA is not included yet.
A15: United Nilgiri holds most of its assets as investments and earns large other income, which is excluded from EBITDA but included in net profit and ROE.

Sheet Tata Consumer
A1: Tata Consumer Products (₹ Crore) | B1: FY21 | C1: FY22 | D1: FY23 | E1: FY24 | F1: FY25 | G1: FY26
A2: Sales | B2: 11602.03 | C2: 12425.37 | D2: 13783.16 | E2: 15205.85 | F2: 17618.3 | G2: 20290.43
A3: Raw Material Cost | B3: 6367.79 | C3: 6323.22 | D3: 7107.06 | E3: 7364.06 | F3: 8986.68 | G3: 10319.26
A4: Change in Inventory | B4: 149.54 | C4: 39.78 | D4: 273.88 | E4: 121.6 | F4: 362.49 | G4: 40.75
A5: Power and Fuel | B5: 97.36 | C5: 123.9 | D5: 149.43 | E5: 156.9 | F5: 156.21 | G5: 161.95
A6: Other Mfr. Exp | B6: 941.75 | C6: 1139.59 | D6: 1578.2 | E6: 1696.28 | F6: 1882.25 | G6: 2138.9
A7: Employee Cost | B7: 970.23 | C7: 1048 | D7: 1120.36 | E7: 1258.59 | F7: 1430.1 | G7: 1661
A8: Selling and admin | B8: 1421.46 | C8: 1691.83 | D8: 1785.26 | E8: 1927.15 | F8: 2253.37 | G8: 2397.91
A9: Other Expenses | B9: 409.22 | C9: 419.83 | D9: 460.26 | E9: 640.37 | F9: 792.83 | G9: 860.36
A10: Net profit | B10: 856.69 | C10: 935.78 | D10: 1203.77 | E10: 1150.33 | F10: 1278.47 | G10: 1542.3
A11: Equity Share Capital | B11: 92.16 | C11: 92.16 | D11: 92.9 | E11: 95.28 | F11: 98.95 | G11: 98.96
A12: Reserves | B12: 14442.35 | C12: 15049.78 | D12: 16183.81 | E12: 15961.51 | F12: 19902.13 | G12: 21688.57
A13: Total Assets | B13: 20217.82 | C13: 21074.87 | D13: 22762.49 | E13: 27878.79 | F13: 31830.62 | G13: 34278.74
A15: Total expenses | B15: =B3-B4+B5+B6+B7+B8+B9 -> 10058.27 | C15: =C3-C4+C5+C6+C7+C8+C9 -> 10706.59 | D15: =D3-D4+D5+D6+D7+D8+D9 -> 11926.69 | E15: =E3-E4+E5+E6+E7+E8+E9 -> 12921.75 | F15: =F3-F4+F5+F6+F7+F8+F9 -> 15138.95 | G15: =G3-G4+G5+G6+G7+G8+G9 -> 17498.63
A16: Operating profit (EBITDA) | B16: =B2-B15 -> 1543.76 | C16: =C2-C15 -> 1718.78 | D16: =D2-D15 -> 1856.47 | E16: =E2-E15 -> 2284.1 | F16: =F2-F15 -> 2479.35 | G16: =G2-G15 -> 2791.8
A17: EBITDA margin | B17: =B16/B2 -> 0.13305947 | C17: =C16/C2 -> 0.13832828 | D17: =D16/D2 -> 0.13469117 | E17: =E16/E2 -> 0.15021193 | F17: =F16/F2 -> 0.14072584 | G17: =G16/G2 -> 0.13759196
A18: Net margin | B18: =B10/B2 -> 0.073839664 | C18: =C10/C2 -> 0.075312043 | D18: =D10/D2 -> 0.087336286 | E18: =E10/E2 -> 0.07565049 | F18: =F10/F2 -> 0.07256489 | G18: =G10/G2 -> 0.076011203
A19: ROE | B19: =B10/(B11+B12) -> 0.058941788 | C19: =C10/(C11+C12) -> 0.061800535 | D19: =D10/(D11+D12) -> 0.073956592 | E19: =E10/(E11+E12) -> 0.071641343 | F19: =F10/(F11+F12) -> 0.063920048 | G19: =G10/(G11+G12) -> 0.070788199
A20: Asset turnover (x) | B20: =B2/B13 -> 0.57385168 | C20: =C2/C13 -> 0.58958228 | D20: =D2/D13 -> 0.60552075 | E20: =E2/E13 -> 0.54542719 | F20: =F2/F13 -> 0.55350163 | G20: =G2/G13 -> 0.59192462
A21: Revenue growth | B21: n/a | C21: =C2/B2-1 -> 0.070965167 | D21: =D2/C2-1 -> 0.10927562 | E21: =E2/D2-1 -> 0.10321944 | F21: =F2/E2-1 -> 0.15865276 | G21: =G2/F2-1 -> 0.15166787
A23: Sales CAGR, FY21 to FY26 (5 yrs) | B23: =(G2/B2)^(1/5)-1 -> 0.11828231
A25: Blue = numbers from the Screener Data Sheet export (₹ Crore, years end 31 March). Black = formulas.
A26: Total expenses = Raw material − Change in inventory + Power & fuel + Other mfr + Employee + Selling & admin + Other expenses.

Sheet Goodricke
A1: Goodricke Group (₹ Crore) | B1: FY21 | C1: FY22 | D1: FY23 | E1: FY24 | F1: FY25 | G1: FY26
A2: Sales | B2: 891.56 | C2: 823.12 | D2: 882.2 | E2: 823.98 | F2: 929.44 | G2: 801.29
A3: Raw Material Cost | B3: 357.8 | C3: 269.73 | D3: 292.86 | E3: 261.39 | F3: 322.42 | G3: 245.43
A4: Change in Inventory | B4: 0.68 | C4: -4.18 | D4: -1.96 | E4: -7.11 | F4: 9.93 | G4: 5.91
A5: Power and Fuel | B5: 51.97 | C5: 52.96 | D5: 62.11 | E5: 60.59 | F5: 56.89 | G5: 51.18
A6: Other Mfr. Exp | B6: 45 | C6: 51.16 | D6: 60.4 | E6: 66.64 | F6: 72.33 | G6: 65.75
A7: Employee Cost | B7: 295.13 | C7: 320.8 | D7: 339.66 | E7: 369.69 | F7: 365.24 | G7: 333.85
A8: Selling and admin | B8: 64.83 | C8: 62.3 | D8: 70.81 | E8: 61.41 | F8: 61.36 | G8: 54.57
A9: Other Expenses | B9: 32.78 | C9: 35.75 | D9: 44.94 | E9: 45.69 | F9: 41.9 | G9: 36.94
A10: Net profit | B10: 19.53 | C10: 5.28 | D10: -0.32 | E10: -69.3 | F10: 20.06 | G10: 25.55
A11: Equity Share Capital | B11: 21.6 | C11: 21.6 | D11: 21.6 | E11: 21.6 | F11: 21.6 | G11: 21.6
A12: Reserves | B12: 297.73 | C12: 300.84 | D12: 289.29 | E12: 219.64 | F12: 248.95 | G12: 281.9
A13: Total Assets | B13: 663.06 | C13: 636.17 | D13: 639.23 | E13: 648.15 | F13: 641.37 | G13: 598.7
A15: Total expenses | B15: =B3-B4+B5+B6+B7+B8+B9 -> 846.83 | C15: =C3-C4+C5+C6+C7+C8+C9 -> 796.88 | D15: =D3-D4+D5+D6+D7+D8+D9 -> 872.74 | E15: =E3-E4+E5+E6+E7+E8+E9 -> 872.52 | F15: =F3-F4+F5+F6+F7+F8+F9 -> 910.21 | G15: =G3-G4+G5+G6+G7+G8+G9 -> 781.81
A16: Operating profit (EBITDA) | B16: =B2-B15 -> 44.73 | C16: =C2-C15 -> 26.24 | D16: =D2-D15 -> 9.46 | E16: =E2-E15 -> -48.54 | F16: =F2-F15 -> 19.23 | G16: =G2-G15 -> 19.48
A17: EBITDA margin | B17: =B16/B2 -> 0.050170488 | C17: =C16/C2 -> 0.031878705 | D17: =D16/D2 -> 0.010723192 | E17: =E16/E2 -> -0.058909197 | F17: =F16/F2 -> 0.020689878 | G17: =G16/G2 -> 0.024310799
A18: Net margin | B18: =B10/B2 -> 0.021905424 | C18: =C10/C2 -> 0.0064146176 | D18: =D10/D2 -> -0.00036272954 | E18: =E10/E2 -> -0.084103983 | F18: =F10/F2 -> 0.021582889 | G18: =G10/G2 -> 0.031886084
A19: ROE | B19: =B10/(B11+B12) -> 0.061159302 | C19: =C10/(C11+C12) -> 0.01637514 | D19: =D10/(D11+D12) -> -0.001029303 | E19: =E10/(E11+E12) -> -0.28726579 | F19: =F10/(F11+F12) -> 0.07414526 | G19: =G10/(G11+G12) -> 0.084184514
A20: Asset turnover (x) | B20: =B2/B13 -> 1.3446144 | C20: =C2/C13 -> 1.293868 | D20: =D2/D13 -> 1.3800979 | E20: =E2/E13 -> 1.2712798 | F20: =F2/F13 -> 1.4491479 | G20: =G2/G13 -> 1.3383832
A21: Revenue growth | B21: n/a | C21: =C2/B2-1 -> -0.076764323 | D21: =D2/C2-1 -> 0.071775683 | E21: =E2/D2-1 -> -0.065994106 | F21: =F2/E2-1 -> 0.12798854 | G21: =G2/F2-1 -> -0.13787872
A23: Sales CAGR, FY21 to FY26 (5 yrs) | B23: =(G2/B2)^(1/5)-1 -> -0.021123665
A25: Blue = numbers from the Screener Data Sheet export (₹ Crore, years end 31 March). Black = formulas.
A26: Total expenses = Raw material − Change in inventory + Power & fuel + Other mfr + Employee + Selling & admin + Other expenses.

Sheet United Nilgiri
A1: United Nilgiri Tea Estates (₹ Crore) | B1: FY21 | C1: FY22 | D1: FY23 | E1: FY24 | F1: FY25 | G1: FY26
A2: Sales | B2: 66.32 | C2: 75.66 | D2: 83.65 | E2: 84.02 | F2: 89.8 | G2: 83.35
A3: Raw Material Cost | B3: 19.1 | C3: 16.53 | D3: 18.5 | E3: 17.77 | F3: 18.43 | G3: 15.5
A4: Change in Inventory | B4: 3.72 | C4: -0.91 | D4: -2.06 | E4: -0.44 | F4: -3.13 | G4: 1.09
A5: Power and Fuel | B5: 3.68 | C5: 4.82 | D5: 5.31 | E5: 5.24 | F5: 5.73 | G5: 6
A6: Other Mfr. Exp | B6: 10.95 | C6: 13.19 | D6: 12.15 | E6: 7.35 | F6: 7.51 | G6: 7.11
A7: Employee Cost | B7: 20.21 | C7: 22.74 | D7: 23.63 | E7: 24.82 | F7: 23 | G7: 23.96
A8: Selling and admin | B8: 3.45 | C8: 4.6 | D8: 5.9 | E8: 9.99 | F8: 14.35 | G8: 9.96
A9: Other Expenses | B9: 1.86 | C9: 1.77 | D9: 2.35 | E9: 1.98 | F9: 2.29 | G9: 2.08
A10: Net profit | B10: 12.25 | C10: 10.29 | D10: 12.12 | E10: 16.05 | F10: 18.51 | G10: 21.94
A11: Equity Share Capital | B11: 5 | C11: 5 | D11: 5 | E11: 5 | F11: 5 | G11: 5
A12: Reserves | B12: 160.55 | C12: 170.27 | D12: 182.11 | E12: 199.23 | F12: 215.52 | G12: 236.29
A13: Total Assets | B13: 177.14 | C13: 186.86 | D13: 198.08 | E13: 216.93 | F13: 233.1 | G13: 255.65
A15: Total expenses | B15: =B3-B4+B5+B6+B7+B8+B9 -> 55.53 | C15: =C3-C4+C5+C6+C7+C8+C9 -> 64.56 | D15: =D3-D4+D5+D6+D7+D8+D9 -> 69.9 | E15: =E3-E4+E5+E6+E7+E8+E9 -> 67.59 | F15: =F3-F4+F5+F6+F7+F8+F9 -> 74.44 | G15: =G3-G4+G5+G6+G7+G8+G9 -> 63.52
A16: Operating profit (EBITDA) | B16: =B2-B15 -> 10.79 | C16: =C2-C15 -> 11.1 | D16: =D2-D15 -> 13.75 | E16: =E2-E15 -> 16.43 | F16: =F2-F15 -> 15.36 | G16: =G2-G15 -> 19.83
A17: EBITDA margin | B17: =B16/B2 -> 0.16269602 | C17: =C16/C2 -> 0.14670896 | D17: =D16/D2 -> 0.16437537 | E17: =E16/E2 -> 0.19554868 | F17: =F16/F2 -> 0.17104677 | G17: =G16/G2 -> 0.23791242
A18: Net margin | B18: =B10/B2 -> 0.18471049 | C18: =C10/C2 -> 0.13600317 | D18: =D10/D2 -> 0.14488942 | E18: =E10/E2 -> 0.19102595 | F18: =F10/F2 -> 0.20612472 | G18: =G10/G2 -> 0.26322735
A19: ROE | B19: =B10/(B11+B12) -> 0.073995772 | C19: =C10/(C11+C12) -> 0.05870942 | D19: =D10/(D11+D12) -> 0.064774731 | E19: =E10/(E11+E12) -> 0.078587867 | F19: =F10/(F11+F12) -> 0.083937965 | G19: =G10/(G11+G12) -> 0.090927929
A20: Asset turnover (x) | B20: =B2/B13 -> 0.37439314 | C20: =C2/C13 -> 0.40490207 | D20: =D2/D13 -> 0.42230412 | E20: =E2/E13 -> 0.38731388 | F20: =F2/F13 -> 0.38524239 | G20: =G2/G13 -> 0.32603168
A21: Revenue growth | B21: n/a | C21: =C2/B2-1 -> 0.14083233 | D21: =D2/C2-1 -> 0.10560402 | E21: =E2/D2-1 -> 0.0044231919 | F21: =F2/E2-1 -> 0.068793144 | G21: =G2/F2-1 -> -0.071826281
A23: Sales CAGR, FY21 to FY26 (5 yrs) | B23: =(G2/B2)^(1/5)-1 -> 0.046772289
A25: Blue = numbers from the Screener Data Sheet export (₹ Crore, years end 31 March). Black = formulas.
A26: Total expenses = Raw material − Change in inventory + Power & fuel + Other mfr + Employee + Selling & admin + Other expenses.
